stamps/__init__.py
stamps/authentication.py
stamps/base_api.py
stamps/client.py
stamps/exceptions.py
stamps/memberships.py
stamps/redemptions.py
stamps/rewards.py
stamps/transactions.py
stamps_python-0.1.2.dist-info/DESCRIPTION.rst
stamps_python-0.1.2.dist-info/METADATA
stamps_python-0.1.2.dist-info/RECORD
stamps_python-0.1.2.dist-info/WHEEL
stamps_python-0.1.2.dist-info/metadata.json
stamps_python-0.1.2.dist-info/top_level.txt
