Metadata-Version: 2.0
Name: stamps-python
Version: 0.1.2
Summary: Stamps python SDK
Home-page: https://github.com/ui/stamps-python/
Author: PT Stampindo Lancar Jaya
Author-email: selwin@stamps.co.id
License: MIT
Keywords: stamps API
Platform: UNKNOWN
Classifier: Development Status :: 3 - Alpha
Classifier: Intended Audience :: Developers
Classifier: License :: OSI Approved :: MIT License
Classifier: Programming Language :: Python :: 2
Classifier: Programming Language :: Python :: 3
Requires-Dist: requests
Provides-Extra: dev
Provides-Extra: test
